csvmeta/__init__.py
csvmeta/read.py
csvmeta/write.py
csvmeta-1.1.2.dist-info/LICENSE
csvmeta-1.1.2.dist-info/METADATA
csvmeta-1.1.2.dist-info/WHEEL
csvmeta-1.1.2.dist-info/top_level.txt
csvmeta-1.1.2.dist-info/RECORD
