Metadata-Version: 2.1
Name: csvmeta
Version: 1.1.2
Summary: Lightweight csv read/write, keeping track of csv dialect and other metadata.
Author-email: Olivier Binette <olivier@olivierbinette.ca>
Project-URL: homepage, https://github.com/OlivierBinette/CSVMeta
Project-URL: Issues, https://github.com/OlivierBinette/CSVMeta/issues
Classifier: Programming Language :: Python :: 3
Classifier: License :: OSI Approved :: MIT License
Classifier: Operating System :: OS Independent
Requires-Python: >=3.7
License-File: LICENSE
Provides-Extra: dev
Requires-Dist: black ; extra == 'dev'
Requires-Dist: isort ; extra == 'dev'
Provides-Extra: test
Requires-Dist: pytest ; extra == 'test'
Requires-Dist: pytest-cov ; extra == 'test'
